StyledWidgets/TableStyles.py
StyledWidgets/__init__.py
styled_pyqtwidgets-0.1.6.dist-info/METADATA
styled_pyqtwidgets-0.1.6.dist-info/WHEEL
styled_pyqtwidgets-0.1.6.dist-info/top_level.txt
styled_pyqtwidgets-0.1.6.dist-info/RECORD
