Metadata-Version: 2.1
Name: styled-pyqtwidgets
Version: 0.1.6
Summary: create stylized table widget
Author: Dixon Leuenberger
License: UNKNOWN
Keywords: qTableWidget,pypi,package
Platform: UNKNOWN
Classifier: Development Status :: 4 - Beta
Classifier: Intended Audience :: Developers
Classifier: Topic :: Software Development :: Build Tools
Classifier: Programming Language :: Python :: 3.8
Classifier: Programming Language :: Python :: 3.9
Classifier: Programming Language :: Python :: 3 :: Only
Classifier: Operating System :: OS Independent
Requires-Python: >=3.6
Requires-Dist: pyqt5
Provides-Extra: dev
Requires-Dist: check-manifest ; extra == 'dev'
